BeatNet/BeatNet.py
BeatNet/__init__.py
BeatNet/common.py
BeatNet/example.py
BeatNet/log_spect.py
BeatNet/model.py
BeatNet/particle_filtering_cascade.py
BeatNet/models/__init__.py
BeatNet/models/model-1.pt
BeatNet/models/model-2.pt
BeatNet/models/model-3.pt
BeatNet/models/model_1_weights.pt
BeatNet/models/model_2_weights.pt
BeatNet/models/model_3_weights.pt
BeatNet/test_data/808kick120bpm.mp3
BeatNet-1.1.3.dist-info/LICENSE
BeatNet-1.1.3.dist-info/METADATA
BeatNet-1.1.3.dist-info/WHEEL
BeatNet-1.1.3.dist-info/top_level.txt
BeatNet-1.1.3.dist-info/RECORD
